README.md
setup.cfg
setup.py
py3hlda/__init__.py
py3hlda/sampler.py
py3hlda.egg-info/PKG-INFO
py3hlda.egg-info/SOURCES.txt
py3hlda.egg-info/dependency_links.txt
py3hlda.egg-info/not-zip-safe
py3hlda.egg-info/top_level.txt