Metadata-Version: 1.0
Name: py3hlda
Version: 0.1.1
Summary: Gibbs sampler for the Hierarchical Latent Dirichlet Allocation topic model. This is based on the hLDA implementation from Mallet, having a fixed depth on the nCRP tree.
Home-page: https://github.com/Jiannan28/hlda
Author: co
Author-email: UNKNOWN
License: UNKNOWN
Keywords: topic,model,lda,gibbs,sampler,hlda
Platform: UNKNOWN
